Workbook
Name NativeTimeline_Date: #N/A
Name Slicer_Region: #N/A

Sheet Dashboard

Sheet Analysis
A1: Raw Data
A3: 1) Date And Time Function
A4: Select Trancation_ID | B4: TRX0127
A11: {=TRANSPOSE(INDIRECT("'"&$A$1&"'!A1:O1"))} -> Transaction_ID | B11: {=TRANSPOSE(_xlfn.XLOOKUP(B4,'Raw Data'!$A$2:$A$251,'Raw Data'!A2:O251))} -> TRX0127 | D11: Transction Month Last Date | F11: =EOMONTH(B12,0) -> 45473
A12: Date | B12: 45472 | D12: Customer Period Time | F12: =DATEDIF(B24,TODAY(),"Y") &" Year " &DATEDIF(B24,TODAY(),"ym")& "Month "&DATEDIF(B24,TODAY(),"md")& "DAYS" -> 3 Year 11Month 23DAYS
A13: Months | B13: June | D13: Current Time and Date | F13: =NOW() -> 46305.37
A14: Customer_ID | B14: CUST030
A15: Customer_Name | B15: Helen Roberts
A16: Product_ID | B16: P008
A17: Product_Name | B17: Bookshelf
A18: Category | B18: Furniture
A19: Quantity | B19: 1
A20: Unit_Price | B20: 149.99
A21: Payment_Method | B21: PayPal
A22: Region | B22: East
A23: Customer_Segment | B23: Basic
A24: Customer_Since | B24: 44851
A25: Total_Amount | B25: 149.99
A28: 2) Filter Function Top 5
A29: Select Region | B29: Central
A32: {=INDIRECT("'"&$A1&"'!A1:O1")} -> Transaction_ID | B32: Date | C32: Months | D32: Customer_ID | E32: Customer_Name | F32: Product_ID | G32: Product_Name | H32: Category | I32: Quantity | J32: Unit_Price | K32: Payment_Method | L32: Region | M32: Customer_Segment | N32: Customer_Since | O32: Total_Amount
A33: {=_xlfn.TAKE(_xlfn._xlws.SORT(_xlfn._xlws.FILTER('Raw Data'!$A$2:$O$251,'Raw Data'!L2:L251=Analysis!B29,"-"),15,-1),5)} -> TRX0030 | B33: 45686 | C33: January | D33: CUST011 | E33: William White | F33: P001 | G33: Laptop | H33: Electronics | I33: 4 | J33: 899.99 | K33: PayPal | L33: Central | M33: Basic | N33: 44734 | O33: 3599.96
A34: TRX0034 | B34: 45581 | C34: October | D34: CUST049 | E34: Raymond Ross | F34: P002 | G34: Smartphone | H34: Electronics | I34: 4 | J34: 699.99 | K34: Credit Card | L34: Central | M34: Basic | N34: 45385 | O34: 2799.96
A35: TRX0144 | B35: 45749 | C35: April | D35: CUST029 | E35: Edward Mitchell | F35: P001 | G35: Laptop | H35: Electronics | I35: 3 | J35: 899.99 | K35: Cash | L35: Central | M35: Standard | N35: 44953 | O35: 2699.97
A36: TRX0125 | B36: 45666 | C36: January | D36: CUST026 | E36: Karen Hill | F36: P002 | G36: Smartphone | H36: Electronics | I36: 3 | J36: 699.99 | K36: Credit Card | L36: Central | M36: Premium | N36: 45105 | O36: 2099.97
A37: TRX0059 | B37: 45673 | C37: January | D37: CUST016 | E37: Elizabeth Hall | F37: P007 | G37: Desk | H37: Furniture | I37: 5 | J37: 299.99 | K37: Debit Card | L37: Central | M37: Basic | N37: 44431 | O37: 1499.95
A41: 3) What-if-Analysis
A42: Product List | B42: Total Amount | C42: Total Quantity
A43: {=_xlfn.UNIQUE('Raw Data'!$G$2:$G$251)} -> Coffee Maker | B43: =SUMIF('Raw Data'!$G$2:$G$251,Analysis!$A43,'Raw Data'!$O$2:$O$251) -> 3119.61 | C43: =SUMIF('Raw Data'!$G$2:$G$251,Analysis!$A43,'Raw Data'!$I$2:$I$251) -> 39 | E43: Select Product | F43: Coffee Maker
A44: Desk | B44: =SUMIF('Raw Data'!$G$2:$G$251,Analysis!$A44,'Raw Data'!$O$2:$O$251) -> 23399.22 | C44: =SUMIF('Raw Data'!$G$2:$G$251,Analysis!$A44,'Raw Data'!$I$2:$I$251) -> 78 | H44: Total Amount | I44: =SUM('Raw Data'!$O$2:$O$251) -> 229192.47
A45: Bookshelf | B45: =SUMIF('Raw Data'!$G$2:$G$251,Analysis!$A45,'Raw Data'!$O$2:$O$251) -> 15298.98 | C45: =SUMIF('Raw Data'!$G$2:$G$251,Analysis!$A45,'Raw Data'!$I$2:$I$251) -> 102 | E45: Price Amount | F45: {=_xlfn.XLOOKUP(F43,_xlfn.ANCHORARRAY($A$43),$B$43:$B$52)} -> 3119.61 | H45: Expected Growth % | I45: 0.2
A46: Keyboard | B46: =SUMIF('Raw Data'!$G$2:$G$251,Analysis!$A46,'Raw Data'!$O$2:$O$251) -> 8009.11 | C46: =SUMIF('Raw Data'!$G$2:$G$251,Analysis!$A46,'Raw Data'!$I$2:$I$251) -> 89 | E46: Quantity | F46: {=_xlfn.XLOOKUP(F43,_xlfn.ANCHORARRAY(A43),C43:C52)} -> 39 | H46: Final Amount | I46: =I44*(1+I45) -> 275030.96
A47: Headphones | B47: =SUMIF('Raw Data'!$G$2:$G$251,Analysis!$A47,'Raw Data'!$O$2:$O$251) -> 7049.53 | C47: =SUMIF('Raw Data'!$G$2:$G$251,Analysis!$A47,'Raw Data'!$I$2:$I$251) -> 47 | E47: Final Amount | F47: =F45*F46 -> 121664.79
A48: Blender | B48: =SUMIF('Raw Data'!$G$2:$G$251,Analysis!$A48,'Raw Data'!$O$2:$O$251) -> 5219.13 | C48: =SUMIF('Raw Data'!$G$2:$G$251,Analysis!$A48,'Raw Data'!$I$2:$I$251) -> 87
A49: Smartphone | B49: =SUMIF('Raw Data'!$G$2:$G$251,Analysis!$A49,'Raw Data'!$O$2:$O$251) -> 67199.04 | C49: =SUMIF('Raw Data'!$G$2:$G$251,Analysis!$A49,'Raw Data'!$I$2:$I$251) -> 96 | E49: Set Gol change Quantity | H49: Set Gol change Price
A50: Monitor | B50: =SUMIF('Raw Data'!$G$2:$G$251,Analysis!$A50,'Raw Data'!$O$2:$O$251) -> 21999.12 | C50: =SUMIF('Raw Data'!$G$2:$G$251,Analysis!$A50,'Raw Data'!$I$2:$I$251) -> 88
A51: Laptop | B51: =SUMIF('Raw Data'!$G$2:$G$251,Analysis!$A51,'Raw Data'!$O$2:$O$251) -> 67499.25 | C51: =SUMIF('Raw Data'!$G$2:$G$251,Analysis!$A51,'Raw Data'!$I$2:$I$251) -> 75 | E51: Price Amount | F51: =F45 -> 3119.61 | H51: Price Amount | I51: 30769.231
A52: Office Chair | B52: =SUMIF('Raw Data'!$G$2:$G$251,Analysis!$A52,'Raw Data'!$O$2:$O$251) -> 10399.48 | C52: =SUMIF('Raw Data'!$G$2:$G$251,Analysis!$A52,'Raw Data'!$I$2:$I$251) -> 52 | E52: Quantity | F52: 384.66347 | H52: Quantity | I52: =F46 -> 39
E53: Final Amount | F53: =F51*F52 -> 1200000 | H53: Final Amount | I53: =I51*I52 -> 1200000
A56: 4) Conditional Formating
A57: Month | B57: Total Amount | C57: Growth Status
A58: January | B58: =SUMIF('Raw Data'!$C$2:$C$251,Analysis!$A58,'Raw Data'!$O$2:$O$251) -> 25799.15 | C58: -
A59: February | B59: =SUMIF('Raw Data'!$C$2:$C$251,Analysis!$A59,'Raw Data'!$O$2:$O$251) -> 16069.38 | C59: =($B59-$B58)/$B58 -> -0.37713529
A60: March | B60: =SUMIF('Raw Data'!$C$2:$C$251,Analysis!$A60,'Raw Data'!$O$2:$O$251) -> 19899.38 | C60: =($B60-$B59)/$B59 -> 0.23834149
A61: April | B61: =SUMIF('Raw Data'!$C$2:$C$251,Analysis!$A61,'Raw Data'!$O$2:$O$251) -> 27899.16 | C61: =($B61-$B60)/$B60 -> 0.40201152
A62: May | B62: =SUMIF('Raw Data'!$C$2:$C$251,Analysis!$A62,'Raw Data'!$O$2:$O$251) -> 17039.35 | C62: =($B62-$B61)/$B61 -> -0.38925222
A63: June | B63: =SUMIF('Raw Data'!$C$2:$C$251,Analysis!$A63,'Raw Data'!$O$2:$O$251) -> 19299.45 | C63: =($B63-$B62)/$B62 -> 0.13264004
A64: July | B64: =SUMIF('Raw Data'!$C$2:$C$251,Analysis!$A64,'Raw Data'!$O$2:$O$251) -> 18479.4 | C64: =($B64-$B63)/$B63 -> -0.042490848
A65: August | B65: =SUMIF('Raw Data'!$C$2:$C$251,Analysis!$A65,'Raw Data'!$O$2:$O$251) -> 15759.43 | C65: =($B65-$B64)/$B64 -> -0.1471893
A66: September | B66: =SUMIF('Raw Data'!$C$2:$C$251,Analysis!$A66,'Raw Data'!$O$2:$O$251) -> 12989.51 | C66: =($B66-$B65)/$B65 -> -0.1757627
A67: October | B67: =SUMIF('Raw Data'!$C$2:$C$251,Analysis!$A67,'Raw Data'!$O$2:$O$251) -> 20609.52 | C67: =($B67-$B66)/$B66 -> 0.58662798
A68: November | B68: =SUMIF('Raw Data'!$C$2:$C$251,Analysis!$A68,'Raw Data'!$O$2:$O$251) -> 12309.44 | C68: =($B68-$B67)/$B67 -> -0.40273039
A69: December | B69: =SUMIF('Raw Data'!$C$2:$C$251,Analysis!$A69,'Raw Data'!$O$2:$O$251) -> 23039.3 | C69: =($B69-$B68)/$B68 -> 0.87167735 | F69: SUMMARY OUTPUT
F71: Regression Statistics
A72: 5) Linear Regression | F72: Multiple R | G72: 0.36265289
A73: Product List | B73: Total Quantity | C73: Total Amount | F73: R Square | G73: 0.13151712
A74: {=_xlfn.UNIQUE('Raw Data'!$G$2:$G$251)} -> Coffee Maker | B74: =SUMIF('Raw Data'!$G$2:$G$251,Analysis!$A74,'Raw Data'!$I$2:$I$251) -> 39 | C74: =SUMIF('Raw Data'!$G$2:$G$251,Analysis!$A74,'Raw Data'!$O$2:$O$251) -> 3119.61 | F74: Adjusted R Square | G74: 0.022956757
A75: Desk | B75: =SUMIF('Raw Data'!$G$2:$G$251,Analysis!$A75,'Raw Data'!$I$2:$I$251) -> 78 | C75: =SUMIF('Raw Data'!$G$2:$G$251,Analysis!$A75,'Raw Data'!$O$2:$O$251) -> 23399.22 | F75: Standard Error | G75: 21.595976
A76: Bookshelf | B76: =SUMIF('Raw Data'!$G$2:$G$251,Analysis!$A76,'Raw Data'!$I$2:$I$251) -> 102 | C76: =SUMIF('Raw Data'!$G$2:$G$251,Analysis!$A76,'Raw Data'!$O$2:$O$251) -> 15298.98 | F76: Observations | G76: 10
A77: Keyboard | B77: =SUMIF('Raw Data'!$G$2:$G$251,Analysis!$A77,'Raw Data'!$I$2:$I$251) -> 89 | C77: =SUMIF('Raw Data'!$G$2:$G$251,Analysis!$A77,'Raw Data'!$O$2:$O$251) -> 8009.11
A78: Headphones | B78: =SUMIF('Raw Data'!$G$2:$G$251,Analysis!$A78,'Raw Data'!$I$2:$I$251) -> 47 | C78: =SUMIF('Raw Data'!$G$2:$G$251,Analysis!$A78,'Raw Data'!$O$2:$O$251) -> 7049.53 | F78: ANOVA
A79: Blender | B79: =SUMIF('Raw Data'!$G$2:$G$251,Analysis!$A79,'Raw Data'!$I$2:$I$251) -> 87 | C79: =SUMIF('Raw Data'!$G$2:$G$251,Analysis!$A79,'Raw Data'!$O$2:$O$251) -> 5219.13 | G79: df | H79: SS | I79: MS | J79: F | K79: Significance F
A80: Smartphone | B80: =SUMIF('Raw Data'!$G$2:$G$251,Analysis!$A80,'Raw Data'!$I$2:$I$251) -> 96 | C80: =SUMIF('Raw Data'!$G$2:$G$251,Analysis!$A80,'Raw Data'!$O$2:$O$251) -> 67199.04 | F80: Regression | G80: 1 | H80: 565.01069 | I80: 565.01069 | J80: 1.2114654 | K80: 0.30305462
A81: Monitor | B81: =SUMIF('Raw Data'!$G$2:$G$251,Analysis!$A81,'Raw Data'!$I$2:$I$251) -> 88 | C81: =SUMIF('Raw Data'!$G$2:$G$251,Analysis!$A81,'Raw Data'!$O$2:$O$251) -> 21999.12 | F81: Residual | G81: 8 | H81: 3731.0893 | I81: 466.38616
A82: Laptop | B82: =SUMIF('Raw Data'!$G$2:$G$251,Analysis!$A82,'Raw Data'!$I$2:$I$251) -> 75 | C82: =SUMIF('Raw Data'!$G$2:$G$251,Analysis!$A82,'Raw Data'!$O$2:$O$251) -> 67499.25 | F82: Total | G82: 9 | H82: 4296.1
A83: Office Chair | B83: =SUMIF('Raw Data'!$G$2:$G$251,Analysis!$A83,'Raw Data'!$I$2:$I$251) -> 52 | C83: =SUMIF('Raw Data'!$G$2:$G$251,Analysis!$A83,'Raw Data'!$O$2:$O$251) -> 10399.48
G84: Coefficients | H84: Standard Error | I84: t Stat | J84: P-value | K84: Lower 95% | L84: Upper 95% | M84: Lower 95.0% | N84: Upper 95.0%
F85: Intercept | G85: 67.847226 | H85: 9.6170208 | I85: 7.0549111 | J85: 0.00010664833 | K85: 45.670337 | L85: 90.024116 | M85: 45.670337 | N85: 90.024116
F86: X Variable 1 | G86: 0.00032517533 | H86: 0.0002954351 | I86: 1.1006659 | J86: 0.30305462 | K86: -0.00035609923 | L86: 0.0010064499 | M86: -0.00035609923 | N86: 0.0010064499
A87: 6) frequently purchased products
A88: Product List | B88: Frequently Product | C88: frequently purchased products | D88: Total Frequently
A89: {=_xlfn.UNIQUE('Raw Data'!$G$2:$G$251)} -> Coffee Maker | B89: {=COUNTIF('Raw Data'!$G$2:$G$251,_xlfn.ANCHORARRAY(A89))} -> 14 | C89: {=_xlfn.UNIQUE(_xlfn._xlws.FILTER('Raw Data'!G2:G251,COUNTIF('Raw Data'!G2:G251,'Raw Data'!G2:G251)=MODE(COUNTIF('Raw Data'!G2:G251,'Raw Data'!G2:G251))))} -> Desk | D89: {=MODE(COUNTIF('Raw Data'!G2:G251,'Raw Data'!G2:G251))} -> 26
A90: Desk | B90: 26 | C90: Monitor | D90: {=MODE(COUNTIF('Raw Data'!G3:G252,'Raw Data'!G3:G252))} -> 26
A91: Bookshelf | B91: 35
A92: Keyboard | B92: 34
A93: Headphones | B93: 16
A94: Blender | B94: 29
A95: Smartphone | B95: 31
A96: Monitor | B96: 26
A97: Laptop | B97: 24
A98: Office Chair | B98: 15
A104: 7) Compare two List
A105: 8) Abbreviations
A106: Customer | B106: Pyment Method | D106: Customer | E106: Pyment Method | G106: Both Method use Customer | H106: Short Name
A107: {=_xlfn._xlws.FILTER('Raw Data'!$E$2:$E$251,'Raw Data'!$K$2:$K$251='Raw Data'!K2)} -> Lawrence Reed | B107: Cash | D107: {=_xlfn._xlws.FILTER('Raw Data'!$E$2:$E$251,'Raw Data'!$K$2:$K$251='Raw Data'!K14)} -> Dorothy Nelson | E107: Paypal | G107: {=_xlfn.UNIQUE(_xlfn._xlws.FILTER(_xlfn.ANCHORARRAY($A$107),(_xlfn.ANCHORARRAY($A$107)<>"")*(COUNTIF($D$107:$D$182,_xlfn.ANCHORARRAY($A$107))>0)))} -> Lawrence Reed | H107: {=_xlfn.TEXTJOIN(" ", TRUE,LEFT(_xlfn.TEXTSPLIT(G107," "),1))} -> L R
A108: Daniel King | B108: Cash | D108: Jennifer Taylor | E108: Paypal | G108: Emma Wilson | H108: {=_xlfn.TEXTJOIN(" ", TRUE,LEFT(_xlfn.TEXTSPLIT(G108," "),1))} -> E W
A109: Emma Wilson | B109: Cash | D109: Harry Morgan | E109: Paypal | G109: Robert Thomas | H109: {=_xlfn.TEXTJOIN(" ", TRUE,LEFT(_xlfn.TEXTSPLIT(G109," "),1))} -> R T
A110: Patricia Moore | B110: Cash | D110: Arthur Edwards | E110: Paypal | G110: Sarah Davis | H110: {=_xlfn.TEXTJOIN(" ", TRUE,LEFT(_xlfn.TEXTSPLIT(G110," "),1))} -> S D
A111: Ruth Brooks | B111: Cash | D111: William White | E111: Paypal | G111: Lisa Anderson | H111: {=_xlfn.TEXTJOIN(" ", TRUE,LEFT(_xlfn.TEXTSPLIT(G111," "),1))} -> L A
A112: David Martinez | B112: Cash | D112: Nancy Collins | E112: Paypal | G112: Charles Allen | H112: {=_xlfn.TEXTJOIN(" ", TRUE,LEFT(_xlfn.TEXTSPLIT(G112," "),1))} -> C A
A113: Robert Thomas | B113: Cash | D113: Mark Carter | E113: Paypal | G113: Peter Richardson | H113: {=_xlfn.TEXTJOIN(" ", TRUE,LEFT(_xlfn.TEXTSPLIT(G113," "),1))} -> P R
A114: Sarah Davis | B114: Cash | D114: Susan Green | E114: Paypal | G114: Harry Morgan | H114: {=_xlfn.TEXTJOIN(" ", TRUE,LEFT(_xlfn.TEXTSPLIT(G114," "),1))} -> H M
A115: Joseph Jackson | B115: Cash | D115: Edward Mitchell | E115: Paypal | G115: Kathleen Bennett | H115: {=_xlfn.TEXTJOIN(" ", TRUE,LEFT(_xlfn.TEXTSPLIT(G115," "),1))} -> K B
A116: Lisa Anderson | B116: Cash | D116: Virginia Sanders | E116: Paypal | G116: Kevin Scott | H116: {=_xlfn.TEXTJOIN(" ", TRUE,LEFT(_xlfn.TEXTSPLIT(G116," "),1))} -> K S
A117: Betty Campbell | B117: Cash | D117: John Smith | E117: Paypal | G117: Michael Brown | H117: {=_xlfn.TEXTJOIN(" ", TRUE,LEFT(_xlfn.TEXTSPLIT(G117," "),1))} -> M B
A118: Emma Wilson | B118: Cash | D118: Elizabeth Hall | E118: Paypal | G118: Susan Green | H118: {=_xlfn.TEXTJOIN(" ", TRUE,LEFT(_xlfn.TEXTSPLIT(G118," "),1))} -> S G
A119: Charles Allen | B119: Cash | D119: Cynthia Price | E119: Paypal | G119: Dorothy Nelson | H119: {=_xlfn.TEXTJOIN(" ", TRUE,LEFT(_xlfn.TEXTSPLIT(G119," "),1))} -> D N
... A128: Ruth Brooks | B128: Cash | D128: Michael Brown | E128: Paypal | G128: Linda Martin | H128: {=_xlfn.TEXTJOIN(" ", TRUE,LEFT(_xlfn.TEXTSPLIT(G128," "),1))} -> L M
A129: Susan Green | B129: Cash | D129: Linda Martin | E129: Paypal
A130: Dennis Gray | B130: Cash | D130: Douglas Watson | E130: Paypal
...

Sheet Visualizations
A1: 9) Pivot Table Pivot Chart (Bar , Line, pie) , Kpi and Slicers and Timelines , 10) Data Analysis and Storytelling , 11) report and Dashboard
D3: Top Product | H3: Day Transaction | K3: Customer Segment
A4: TotalRevenue | D4: Product | E4: Amount | H4: Days | I4: Count Transaction | K4: Customer Segment | L4: Count of Customer_Segment
A5: 229192.47 | D5: Laptop | E5: 67499.25 | H5: 45393 | I5: 1 | K5: Basic | L5: 0.296
D6: Smartphone | E6: 67199.04 | H6: 45396 | I6: 1 | K6: Premium | L6: 0.38
D7: Desk | E7: 23399.22 | H7: 45399 | I7: 1 | K7: Standard | L7: 0.324
A8: TotalQuantitySold | D8: Monitor | E8: 21999.12 | H8: 45400 | I8: 2
A9: 753 | D9: Bookshelf | E9: 15298.98 | H9: 45403 | I9: 3
D10: Office Chair | E10: 10399.48 | H10: 45405 | I10: 1 | K10: Daynamic Data Storytelling
D11: Keyboard | E11: 8009.11 | H11: 45408 | I11: 4 | K11: Total Customer | L11: =COUNTA(_xlfn.UNIQUE('Raw Data'!D2:D251)) -> 50 | M11: -
A12: Total Transaction | D12: Headphones | E12: 7049.53 | H12: 45409 | I12: 3 | K12: Best-Performing Product | L12: =MAX(B31) -> 67499.25 | M12: =INDEX($A$31:$A$40,MATCH(L12,$B$31:$B$40,0)) -> Laptop
A13: 250 | D13: Blender | E13: 5219.13 | H13: 45410 | I13: 4 | K13: Top Revenue-Generating Customer | L13: =MAX($E$26:$E$76) -> 15659.65 | M13: =INDEX($D$26:$D$76,MATCH(L13,$E$26:$E$76,0)) -> Mark Carter
D14: Coffee Maker | E14: 3119.61 | H14: 45412 | I14: 1 | K14: Top Payment Preference | L14: =MAX(E19:E22) -> 0.304 | M14: =INDEX(D19:D22,MATCH(L14,E19:E22,0)) -> Cash
H15: 45413 | I15: 1
A16: TOP 10 Customer | H16: 45415 | I16: 1
A17: Customer | B17: Amount | D17: Payment Method Distrbution | H17: 45416 | I17: 1
A18: Mark Carter | B18: 15659.65 | D18: Pyment Method | E18: Count of Payment_Method | H18: 45422 | I18: 1
A19: Edward Mitchell | B19: 11919.77 | D19: Cash | E19: 0.304 | H19: 45424 | I19: 3
A20: Barbara Young | B20: 10649.8 | D20: Credit Card | E20: 0.272 | H20: 45425 | I20: 1
A21: Patricia Moore | B21: 9799.73 | D21: Debit Card | E21: 0.216 | H21: 45427 | I21: 2
A22: Paul Baker | B22: 8309.74 | D22: PayPal | E22: 0.208 | H22: 45428 | I22: 1
A23: Dorothy Nelson | B23: 8269.79 | H23: 45430 | I23: 1
A24: Karen Hill | B24: 8009.77 | D24: Top Customer | H24: 45432 | I24: 1
A25: Daniel King | B25: 7309.8 | D25: Row Labels | E25: Sum of Total_Amount | H25: 45434 | I25: 1
A26: Lawrence Reed | B26: 6989.77 | D26: Mark Carter | E26: 15659.65 | H26: 45435 | I26: 1
A27: Joseph Jackson | B27: 6949.84 | H27: 45438 | I27: 1
H28: 45440 | I28: 1
A29: Top Product | H29: 45441 | I29: 1
A30: Row Labels | B30: Sum of Total_Amount | H30: 45443 | I30: 1
A31: Laptop | B31: 67499.25 | H31: 45444 | I31: 2
A32: Smartphone | B32: 67199.04 | H32: 45446 | I32: 1
A33: Desk | B33: 23399.22 | H33: 45449 | I33: 2
A34: Monitor | B34: 21999.12 | H34: 45450 | I34: 1
A35: Bookshelf | B35: 15298.98 | H35: 45452 | I35: 1
A36: Office Chair | B36: 10399.48 | H36: 45456 | I36: 1
A37: Keyboard | B37: 8009.11 | H37: 45459 | I37: 3
A38: Headphones | B38: 7049.53 | H38: 45460 | I38: 2
A39: Blender | B39: 5219.13 | H39: 45468 | I39: 1
A40: Coffee Maker | B40: 3119.61 | H40: 45469 | I40: 2
H41: 45471 | I41: 2
H42: 45472 | I42: 1
H43: 45474 | I43: 1
H44: 45475 | I44: 1
H45: 45476 | I45: 2
H46: 45481 | I46: 3
H47: 45482 | I47: 1
H48: 45484 | I48: 2
H49: 45487 | I49: 1
H50: 45490 | I50: 2
H51: 45491 | I51: 1
H52: 45496 | I52: 1
... H166: 45758 | I166: 3

Sheet Scenario Summary
B2: Scenario Summary
D3: Current Values: | E3: Bast Case | F3: Normal | G3: Worst Case
E4: Created by himanshi on 09-10-2026 Modified by himanshi on 09-10-2026 | F4: Created by himanshi on 09-10-2026 Modified by himanshi on 09-10-2026 | G4: Created by himanshi on 09-10-2026
B5: Changing Cells:
C6: $I$45 | D6: 0.2 | E6: 0.2 | F6: 0.1 | G6: -0.1
B7: Result Cells:
C8: $I$46 | D8: 275030.96 | E8: 275030.96 | F8: 252111.72 | G8: 206273.22
B9: Notes: Current Values column represents values of changing cells at
B10: time Scenario Summary Report was created. Changing cells for each
B11: scenario are highlighted in gray.

Sheet Raw Data
A1: Transaction_ID | B1: Date | C1: Months | D1: Customer_ID | E1: Customer_Name | F1: Product_ID | G1: Product_Name | H1: Category | I1: Quantity | J1: Unit_Price | K1: Payment_Method | L1: Region | M1: Customer_Segment | N1: Customer_Since | O1: Total_Amount
A2: TRX0001 | B2: 45528 | C2: =TEXT(B2,"mmmm") -> August | D2: CUST039 | E2: Lawrence Reed | F2: P004 | G2: Coffee Maker | H2: Appliances | I2: 3 | J2: 79.99 | K2: Cash | L2: Central | M2: Premium | N2: 44779 | O2: 239.97
A3: TRX0002 | B3: 45501 | C3: =TEXT(B3,"mmmm") -> July | D3: CUST019 | E3: Daniel King | F3: P007 | G3: Desk | H3: Furniture | I3: 3 | J3: 299.99 | K3: Cash | L3: Central | M3: Basic | N3: 44732 | O3: 899.97
A4: TRX0003 | B4: 45737 | C4: =TEXT(B4,"mmmm") -> March | D4: CUST002 | E4: Emma Wilson | F4: P008 | G4: Bookshelf | H4: Furniture | I4: 2 | J4: 149.99 | K4: Cash | L4: West | M4: Premium | N4: 45233 | O4: 299.98
A5: TRX0004 | B5: 45424 | C5: =TEXT(B5,"mmmm") -> May | D5: CUST012 | E5: Patricia Moore | F5: P010 | G5: Keyboard | H5: Electronics | I5: 5 | J5: 89.99 | K5: Cash | L5: North | M5: Premium | N5: 44919 | O5: 449.95
A6: TRX0005 | B6: 45550 | C6: =TEXT(B6,"mmmm") -> September | D6: CUST042 | E6: Ruth Brooks | F6: P003 | G6: Headphones | H6: Electronics | I6: 4 | J6: 149.99 | K6: Cash | L6: North | M6: Basic | N6: 44909 | O6: 599.96
A7: TRX0006 | B7: 45498 | C7: =TEXT(B7,"mmmm") -> July | D7: CUST007 | E7: David Martinez | F7: P005 | G7: Blender | H7: Appliances | I7: 2 | J7: 59.99 | K7: Cash | L7: North | M7: Standard | N7: 45152 | O7: 119.98
A8: TRX0007 | B8: 45469 | C8: =TEXT(B8,"mmmm") -> June | D8: CUST009 | E8: Robert Thomas | F8: P010 | G8: Keyboard | H8: Electronics | I8: 2 | J8: 89.99 | K8: Cash | L8: West | M8: Basic | N8: 44438 | O8: 179.98
A9: TRX0008 | B9: 45648 | C9: =TEXT(B9,"mmmm") -> December | D9: CUST007 | E9: David Martinez | F9: P008 | G9: Bookshelf | H9: Furniture | I9: 3 | J9: 149.99 | K9: Debit Card | L9: North | M9: Standard | N9: 44522 | O9: 449.97
A10: TRX0009 | B10: 45588 | C10: =TEXT(B10,"mmmm") -> October | D10: CUST004 | E10: Sarah Davis | F10: P002 | G10: Smartphone | H10: Electronics | I10: 2 | J10: 699.99 | K10: Cash | L10: Central | M10: Basic | N10: 44992 | O10: 1399.98
A11: TRX0010 | B11: 45688 | C11: =TEXT(B11,"mmmm") -> January | D11: CUST026 | E11: Karen Hill | F11: P002 | G11: Smartphone | H11: Electronics | I11: 4 | J11: 699.99 | K11: Debit Card | L11: West | M11: Premium | N11: 44692 | O11: 2799.96
A12: TRX0011 | B12: 45696 | C12: =TEXT(B12,"mmmm") -> February | D12: CUST040 | E12: Sharon Butler | F12: P005 | G12: Blender | H12: Appliances | I12: 5 | J12: 59.99 | K12: Debit Card | L12: Central | M12: Standard | N12: 45177 | O12: 299.95
A13: TRX0012 | B13: 45622 | C13: =TEXT(B13,"mmmm") -> November | D13: CUST045 | E13: Douglas Watson | F13: P009 | G13: Monitor | H13: Electronics | I13: 5 | J13: 249.99 | K13: Credit Card | L13: North | M13: Basic | N13: 44873 | O13: 1249.95
... A251: TRX0250 | B251: 45746 | C251: =TEXT(B251,"mmmm") -> March | D251: CUST026 | E251: Karen Hill | F251: P010 | G251: Keyboard | H251: Electronics | I251: 2 | J251: 89.99 | K251: Debit Card | L251: West | M251: Premium | N251: 44522 | O251: 179.98
